rootpay_sdk/__init__.py
rootpay_sdk/rootpay.py
rootpay_sdk-1.0.0.dist-info/METADATA
rootpay_sdk-1.0.0.dist-info/WHEEL
rootpay_sdk-1.0.0.dist-info/top_level.txt
rootpay_sdk-1.0.0.dist-info/RECORD
